LICENSE
MANIFEST.in
README.rst
setup.cfg
setup.py
themata/__init__.py
themata/themate.py
themata.egg-info/PKG-INFO
themata.egg-info/SOURCES.txt
themata.egg-info/dependency_links.txt
themata.egg-info/entry_points.txt
themata.egg-info/not-zip-safe
themata.egg-info/requires.txt
themata.egg-info/top_level.txt
themata/_static/css/syntaxy.dark.min.css
themata/_static/css/syntaxy.light.min.css
themata/_static/css/syntaxy.purple.min.css
themata/_static/js/microlight.js
themata/_static/js/prism.js
themata/_static/js/syntaxy.min.js
themata/_static/js/themata.js
themata/clear/__init__.py
themata/clear/layout.html
themata/clear/theme.conf
themata/clear/static/css/clear.css_t
themata/fandango/__init__.py
themata/fandango/layout.html
themata/fandango/theme.conf
themata/fandango/static/css/fandango.css_t
themata/fluid/__init__.py
themata/fluid/layout.html
themata/fluid/theme.conf
themata/fluid/static/css/fluid.css_t
themata/garri/__init__.py
themata/garri/layout.html
themata/garri/theme.conf
themata/garri/static/css/garri.css_t
themata/hackish/__init__.py
themata/hackish/layout.html
themata/hackish/theme.conf
themata/hackish/static/css/hackish.css_t
themata/milkish/__init__.py
themata/milkish/layout.html
themata/milkish/theme.conf
themata/milkish/static/css/milkiish.css_t
themata/sugar/__init__.py
themata/sugar/layout.html
themata/sugar/theme.conf
themata/sugar/static/css/sugar.css_t
themata/water/__init__.py
themata/water/layout.html
themata/water/theme.conf
themata/water/static/css/water.css_t