Metadata-Version: 2.1
Name: themata
Version: 1.14
Summary: Set of Highly customizable sphinx themes. hackish, milkish, fandango, clear, fluid, garri, water and sugar.
Home-page: https://github.com/Thecarisma/themata/
Author: Adewale Azeez
Author-email: iamthecarisma@gmail.com
License: CC0 1.0 Universal (CC0 1.0) Public Domain Dedication
Keywords: sphinx,extension,theme,thecarisma,hackish,milkish,fandango,clear,fluid,garri,water,sugar
Platform: UNKNOWN
Classifier: Development Status :: 5 - Production/Stable
Classifier: Intended Audience :: Developers
Classifier: License :: OSI Approved :: Common Public License
Classifier: Operating System :: OS Independent
Classifier: Programming Language :: Python :: 2.5
Classifier: Programming Language :: Python :: 2.6
Classifier: Programming Language :: Python :: 2.7
Classifier: Programming Language :: Python :: 3
Classifier: Topic :: Documentation
Classifier: Topic :: Software Development :: Documentation
License-File: LICENSE
